safelysave/__init__.py
safelysaveonline-3.2.0.dist-info/LICENSE
safelysaveonline-3.2.0.dist-info/METADATA
safelysaveonline-3.2.0.dist-info/WHEEL
safelysaveonline-3.2.0.dist-info/top_level.txt
safelysaveonline-3.2.0.dist-info/RECORD
