Metadata-Version: 2.1
Name: safelysaveonline
Version: 3.2.0
Summary: SafelySaveOnline is a libary making it easy to save encrypted dictionaries and store them in a git repository.
Author: VisualXYW
License: MIT License
Project-URL: Homepage, https://codeberg.org/VisualXYW/safelysaveonline
Project-URL: Issues, https://codeberg.org/VisualXYW/safelysaveonline/issues
Project-URL: Documentation, https://codeberg.org/VisualXYW/safelysaveonline/wiki
Keywords: encrypted,dictionary,git,save,saving,webdav,store
Classifier: Development Status :: 4 - Beta
Classifier: License :: OSI Approved :: MIT License
Classifier: Programming Language :: Python :: 3.12
Classifier: Intended Audience :: Developers
Classifier: Operating System :: OS Independent
Requires-Python: >=3.12
License-File: LICENSE
Requires-Dist: cryptography
Requires-Dist: gitpython
Requires-Dist: webdav4
Requires-Dist: httpx
